[":]c?e?@gBDi?AfjmKLklM`JNcdQbCa`ERfHgITaBfHQdNThVXlOS", ":g`_h?M@J?pXOqPAco?dKCK_cG`CdIDpQ[WTJapg{O\\VLFWHGrFKExo{lSKrraIMLMQQPmEELO@@B", ":ga?HOaACf?`L?\\EDpgW}BNHpPhEhBEPw?UONJprKsjFGEXhGxHJeH`uKOIO__iQKHO?YEIGLOOOj", ":g`_GgCF?@QPCkH?@ro{mXRFCGO}TEIp@SGhCCPwwwtDGcxpYRHGqAhyYQMoR@y]QKqqDGmc_bRSgY^", ":gb?wKcFCeaxwQEG`BgG}gKHpgGeSRdcGwkjGCp?g}IFIO@cgWQ`O_oy?TKRbS?eVgdhhs~GEggh|H", ":g`?GGIM?c_X_ILGCqh[AVOGsg`MEEaTQssnDDCGg}LIGoQcO[QcBB\\]q[NQPxQMLOppXuIWOq@`r", ":ga?WoASFa@O{s@@gBGgqbGi_ADACFCRg[GjIHCxGghLHOOg}EHKr@xaGLHo`xQOSKP`KK[\\bDbTWqc", ":q`_HOeNOBbGcu?A`BxxEmEcax_ylPcEhCyH^a`atSoYadxp]GHLqrYM]QQRAXQCLMO@iAEGOPOxIABGPbHuSUNOPPyA\\N~", ":qb??KECFaoH_e[LcSQDKAM`rwgyMQIsgCUWLLQPxQT^KQaDyGWisa`}ZCOqrHuCRNpAHeU]POpXz?``BCkKyebCQt@EdlGtf", ":qc?XCeLDaS?GQcLGoIK?ADaCGWiPJJRYxaMXbbgWeDJ`FsDgxFHVc[ACMGqckW]aaeCko]R`bqcxHShedcWufeFTl|?l", ":qb?OcEDJ?qxoucEiAh@QRH_BX{gXDKrB[GSLaOrSSb?@SbeIMOfBq[{cXbawXOpOGfg?OJRJhGXLFHIdiqDNMGFyH[|GOG~", ":qc?HOeNBCpgL?VIfrg?SdC`TgWYSQJuoW[t\\FOQsoYN`DWkW_`gfBs[U_gEIXU]RJqPkOxCMGX@uCYrJGHgz?CI[ilZDGiN", ":qa_gwQ@Ae??GYIJdS?[yON`QIwW\\EErqTkEJJOyh[xIKUi@YbFDcZ{cx@HqRS?eSbdS[C^YQXdTPAjaGTKO_bdDQtw}_aeSn", ":qc@XW_TL?RoWiEEhAG?]iAESXKEcUbbgOUWZnAp`EAF`CblozMIqQaEQUKpBDESMLP`l?nCSUCqi?SNoo_}YRPORiUIVRPaaf", ":qa?X?IUE`qw_U?Gh?`k]kDIsYPKhOdO`cCTFItbkCXDDeXTc~EIdx{cuc_CCLOtBNGW?_hHMYg_XHBPHxH\\VFGcxh?tMGi~", ":{a`GwISD`RPS{V?a@iWgdU?bg[shY@bxdeLGJurc_[P_BAEKZMLsHH`FHIGk\\UihmFgyTT@PTBK?rQSiwwaIcSRDjEENMoaiUcaSTrPuAJJQT{W}maCvN", ":{b@HGQUHaRoCAeIEtPSK]PadJGm\\AGPaCctKLo?HM^]aug{KLPIDWO\\FFKHGhEA_eqsLqO\\qIwGx^AEjYPdVQIjXAHJXPq`aqg_SotQyc`PQAxa[WY~", ":{`_GgEMCAr`SmcK_ohC}oVeP`s_`PJQ`kR?AFFhXQfEKfYP}QRKVhP|L@@aKcSnKPRSKGLPIF}?k_[jIXxHLCKjwWdZHIjxh\\DFGeG@TT?Tjy@lRYUK^", ":{b@WCcFCe`pCIaDerxGmkMeCI\\aUXmAqhaCKIrrSYXCCo@DUAI_gKxE[aafyA@FEBf{k?OVhHtcGEenGyq`RPLjKsC_`iEWXHHfYp@PYuoXrrYYerZ~", ":{a?WoA_I`?pDK@FCpiwunDHDZXapBIUgW{xLLpq@NEJHRBiAkZjrg__VK`AtLMkYRQSQY?MQoPxUMYNQS{C\\INGxg{lISo_iIGfWvERU_QTp`aIIGT~", ":{`_HWeGECO?cEJP@qqDEDFhRjGYuImabL{hZbfkL}SXOQ@KK^NLPApqIJlfSDiQ[cECs?mW___l?iUhecSG_]_i[QM[RISRyUo]XrQyMK[RptZQijU^", ":{`_XWIYJg?g?q^IFPGs}\\XBAWwaZWjO@xmIRa`r{om\\dOAkgobaerdqMXfDBCDNBHP?oeQVuPAAuOPmogHYsaWopYYWiikhi|`GPHljDjOHKIadl", ":{caHWI[IbSO\\KOOhT_d?aU_Ags?[NmCxpIZKIEwpUZ_lgkg?TAHOcddBiJHCk_UTeBwh@RTMOPhyE[QOO_eEfUPrYeMbSpRAYgadfUsdAga@qKCqmabBv", ":{b@HOaFL?_xKYXBh_XCA^@ACWhYsOHQYkYfDDezlqk]erhPQtC_DCclDAMgxxeWegqQC_i``Etk[cfriTdKqe_@rcSMWfFd[GSboHClHAmeJZI@t"]